{
  "Doctors": [
    {
      "id": 1,
      "name": "Dr. Rajesh Deshmukh",
      "expertise": "Orthopedic Surgeon",
      "city": "Pune"
    },
    {
      "id": 2,
      "name": "Dr. Priya Patel",
      "expertise": "Cardiologist",
      "city": "Mumbai"
    },
    {
      "id": 3,
      "name": "Dr. Sunil Joshi",
      "expertise": "Dermatologist",
      "city": "Nagpur"
    },
    {
      "id": 4,
      "name": "Dr. Aishwarya Shah",
      "expertise": "Pediatrician",
      "city": "Nashik"
    },
    {
      "id": 5,
      "name": "Dr. Aniket Kumar",
      "expertise": "Neurologist",
      "city": "Aurangabad"
    }
  ]
 
  
}
